duino_scrapper/__init__.py
duino_scappy-1.1.0.dist-info/METADATA
duino_scappy-1.1.0.dist-info/WHEEL
duino_scappy-1.1.0.dist-info/entry_points.txt
duino_scappy-1.1.0.dist-info/top_level.txt
duino_scappy-1.1.0.dist-info/RECORD
