Metadata-Version: 2.1
Name: duino_scappy
Version: 1.1.0
Summary: CIA/NSA-Grade Duino-OSINT Platform
Home-page: https://github.com/yourusername/your-repo
Author: Jalal Mansour
Classifier: Programming Language :: Python :: 3
Classifier: License :: OSI Approved :: MIT License
Classifier: Operating System :: OS Independent
Requires-Python: >=3.6
Requires-Dist: crawl4ai
Requires-Dist: youtube-transcript-api
